<?xml version="1.0" encoding="UTF-8" standalone="no" ?>
<Application>

  <Header>
    <Version val="13030.00"/>
    <WithIsn val="Y"/>
    <_InternalTask val="N"/>
    <IsRoot val="N"/>
    <InIndex val="N"/>
    <UniqueISNConvState val="12"/>
  </Header>

  <ProgramsRepository>
    <Programs>
      <Task MainProgram="N">
        <Header Description="EX_CG01619VCFf_OS" ISN_2="1" LastIsn="2" id="61">
          <Public val="AP00061"/>
          <ExecutionRight comp="-1"/>
          <Resident val="N"/>
          <SQL val="N"/>
          <ReturnValue>
            <ReturnValueAttr/>
            <ParametersAttributes/>
          </ReturnValue>
          <SqlWhereExist val="N"/>
          <TaskType val="B"/>
          <External val="Y"/>
          <Offline val="N"/>
          <FormType val="N"/>
          <DotNetObjectExists val="N"/>
          <LastModified _date="736671" _time="53657" date="08/12/2017" time="14:54:17"/>
        </Header>
        <ItemIsn val="8"/>
        <Resource>
          <DB id="1">
            <DataObject comp="2" obj="1142"/>
            <Access val="R"/>
            <Share val="W"/>
            <Open val="N"/>
            <Cache val="N"/>
            <IdentifyRowModifications val="84"/>
          </DB>
          <DB id="2">
            <DataObject comp="2" obj="3504"/>
            <Access val="R"/>
            <Share val="W"/>
            <Open val="N"/>
            <Cache val="N"/>
            <IdentifyRowModifications val="84"/>
          </DB>
          <Columns/>
        </Resource>
        <Information>
          <Key>
            <Mode val="N"/>
          </Key>
          <DB comp="-1"/>
          <Sort>
            <CLS val="A"/>
          </Sort>
          <ForceRecordDelete DEL="N"/>
          <EndTaskCondition val="Y"/>
          <EvaluateEndCondition val="A"/>
          <InitialMode val="E"/>
          <Locate Direction="A"/>
          <Range Direction="A"/>
          <VarRange/>
          <TaskProperties>
            <SelectionTable val="N"/>
            <ConfirmUpdate CNFU="N"/>
            <ConfirmCancel val="N"/>
            <ErrorStrategy val="A"/>
            <LockingStrategy val="M"/>
            <CacheStrategy val="T"/>
            <ForceRecordSuffix val="N"/>
            <TransactionMode val="P"/>
            <TransactionBegin val="N"/>
            <PreloadView val="N"/>
            <AllowEmptyDataview val="Y"/>
            <KeepCreatedContext val="N"/>
          </TaskProperties>
          <SIDE_WIN>
            <AllowOptions val="N"/>
            <AllowQuery val="Y"/>
            <AllowModify val="Y"/>
            <AllowCreate val="Y"/>
            <AllowDelete val="Y"/>
            <AllowLocate val="Y"/>
            <AllowRange val="Y"/>
            <AllowIndexChange val="Y"/>
            <AllowSorting val="Y"/>
            <AllowIOFiles val="Y"/>
            <RecordCycle val="Y"/>
            <AllowEvents val="N"/>
            <AllowIndexOptimization val="Y"/>
            <AllowLocationInQuery val="Y"/>
            <AllowPrintingData val="N"/>
          </SIDE_WIN>
          <WIN>
            <OpenTaskWindow val="N"/>
            <CloseTaskWindow val="Y"/>
            <ForegroundWindow val="Y"/>
            <FlipFld val="N"/>
            <RefreshTaskWindow ReturnValue="N"/>
          </WIN>
          <BOX>
            <Direction val="V"/>
          </BOX>
        </Information>
        <INT_CMP_LIST_INFO>
          <v>2</v>
        </INT_CMP_LIST_INFO>
        <TaskLogic>
          <LogicUnit id="2" propagate="78">
            <Level val="R"/>
            <Type val="M"/>
            <Scope val="S"/>
            <EngineDirective val="S"/>
            <ShowMessage val="Y"/>
            <Condition val="89"/>
            <Event>
              <EventType val="S"/>
              <PublicObject comp="-1"/>
            </Event>
            <LogicLines>
              <LogicLine>
                <DATAVIEW_SRC FlowIsn="2" Type="M">
                  <Condition val="N"/>
                  <Modifier val="B"/>
                  <Direction val="C"/>
                </DATAVIEW_SRC>
              </LogicLine>
              <LogicLine>
                <LNK Direction="A" EVL_CND="R" FlowIsn="3" Key="1" Mode="R" SortType="8" VIEW="1" VIEWS="4">
                  <DB comp="2" obj="1142"/>
                  <Expanded val="1"/>
                  <Condition val="Y"/>
                </LNK>
              </LogicLine>
              <LogicLine>
                <Select FieldID="1" FlowIsn="4" id="1">
                  <Column val="1"/>
                  <Type val="R"/>
                  <IsParameter val="N"/>
                  <REAL_VNAME_TXT val="IO.Numero OS"/>
                  <Locate MAX="8" MIN="8"/>
                  <DIFF_UPDATE val="T"/>
                  <Condition val="N"/>
                  <Modifier val="S"/>
                  <Direction val="C"/>
                </Select>
              </LogicLine>
              <LogicLine>
                <Select FieldID="2" FlowIsn="5" id="2">
                  <Column val="2"/>
                  <Type val="R"/>
                  <IsParameter val="N"/>
                  <REAL_VNAME_TXT val="IO.Item"/>
                  <Locate MAX="9" MIN="9"/>
                  <DIFF_UPDATE val="T"/>
                  <Condition val="N"/>
                  <Modifier val="S"/>
                  <Direction val="C"/>
                </Select>
              </LogicLine>
              <LogicLine>
                <Select FieldID="3" FlowIsn="6" id="3">
                  <Column val="26"/>
                  <Type val="R"/>
                  <IsParameter val="N"/>
                  <REAL_VNAME_TXT val="IO.Condicao Pagamento"/>
                  <DIFF_UPDATE val="T"/>
                  <Condition val="N"/>
                  <Modifier val="S"/>
                  <Direction val="C"/>
                </Select>
              </LogicLine>
              <LogicLine>
                <Select FieldID="4" FlowIsn="7" id="4">
                  <Column val="27"/>
                  <Type val="R"/>
                  <IsParameter val="N"/>
                  <REAL_VNAME_TXT val="IO.Tipo de Pagamento"/>
                  <DIFF_UPDATE val="T"/>
                  <Condition val="N"/>
                  <Modifier val="S"/>
                  <Direction val="C"/>
                </Select>
              </LogicLine>
              <LogicLine>
                <END_LINK FlowIsn="8"/>
              </LogicLine>
              <LogicLine>
                <LNK Direction="A" EVL_CND="R" FlowIsn="9" Key="2" Mode="R" SortType="14" VIEW="5" VIEWS="4">
                  <DB comp="2" obj="3504"/>
                  <Expanded val="1"/>
                  <Condition val="Y"/>
                </LNK>
              </LogicLine>
              <LogicLine>
                <Select FieldID="5" FlowIsn="10" id="5">
                  <Column val="2"/>
                  <Type val="R"/>
                  <IsParameter val="N"/>
                  <REAL_VNAME_TXT val="CIO.Numero OS"/>
                  <Locate MAX="8" MIN="8"/>
                  <DIFF_UPDATE val="T"/>
                  <Condition val="N"/>
                  <Modifier val="S"/>
                  <Direction val="C"/>
                </Select>
              </LogicLine>
              <LogicLine>
                <Select FieldID="6" FlowIsn="11" id="6">
                  <Column val="3"/>
                  <Type val="R"/>
                  <IsParameter val="N"/>
                  <REAL_VNAME_TXT val="CIO.Item"/>
                  <Locate MAX="9" MIN="9"/>
                  <DIFF_UPDATE val="T"/>
                  <Condition val="N"/>
                  <Modifier val="S"/>
                  <Direction val="C"/>
                </Select>
              </LogicLine>
              <LogicLine>
                <Select FieldID="7" FlowIsn="12" id="7">
                  <Column val="78"/>
                  <Type val="R"/>
                  <IsParameter val="N"/>
                  <REAL_VNAME_TXT val="CIO.Condicao Pagamento Mat"/>
                  <DIFF_UPDATE val="T"/>
                  <Condition val="N"/>
                  <Modifier val="S"/>
                  <Direction val="C"/>
                </Select>
              </LogicLine>
              <LogicLine>
                <Select FieldID="8" FlowIsn="13" id="8">
                  <Column val="75"/>
                  <Type val="R"/>
                  <IsParameter val="N"/>
                  <REAL_VNAME_TXT val="CIO.Tipo Pagamento Materiais"/>
                  <DIFF_UPDATE val="T"/>
                  <Condition val="N"/>
                  <Modifier val="S"/>
                  <Direction val="C"/>
                </Select>
              </LogicLine>
              <LogicLine>
                <END_LINK FlowIsn="14"/>
              </LogicLine>
            </LogicLines>
          </LogicUnit>
          <LogicUnit id="3" propagate="78">
            <Level val="R"/>
            <Type val="S"/>
            <Scope val="S"/>
            <EngineDirective val="S"/>
            <ShowMessage val="Y"/>
            <Condition val="89"/>
            <Event>
              <EventType val="S"/>
              <PublicObject comp="-1"/>
            </Event>
            <Expanded val="1"/>
            <LogicLines>
              <LogicLine>
                <BLOCK EndBlock="22" EndBlockSegment="22" FlowIsn="15" Type="I">
                  <Condition Exp="1"/>
                  <Modifier val="B"/>
                  <Direction val="C"/>
                </BLOCK>
              </LogicLine>
              <LogicLine>
                <Evaluate FlowIsn="16">
                  <Expression val="2"/>
                  <Condition val="Y"/>
                  <Modifier val="B"/>
                  <Direction val="C"/>
                </Evaluate>
              </LogicLine>
              <LogicLine>
                <Evaluate FlowIsn="17">
                  <Expression val="4"/>
                  <Condition val="Y"/>
                  <Modifier val="B"/>
                  <Direction val="C"/>
                </Evaluate>
              </LogicLine>
              <LogicLine>
                <Evaluate FlowIsn="18">
                  <Expression val="5"/>
                  <Condition val="Y"/>
                  <Modifier val="B"/>
                  <Direction val="C"/>
                </Evaluate>
              </LogicLine>
              <LogicLine>
                <Evaluate FlowIsn="19">
                  <Expression val="6"/>
                  <Condition val="Y"/>
                  <Modifier val="B"/>
                  <Direction val="C"/>
                </Evaluate>
              </LogicLine>
              <LogicLine>
                <Evaluate FlowIsn="20">
                  <Expression val="7"/>
                  <Condition val="Y"/>
                  <Modifier val="B"/>
                  <Direction val="C"/>
                </Evaluate>
              </LogicLine>
              <LogicLine>
                <Evaluate FlowIsn="21">
                  <Expression val="3"/>
                  <Condition val="Y"/>
                  <Modifier val="B"/>
                  <Direction val="C"/>
                </Evaluate>
              </LogicLine>
              <LogicLine>
                <END_BLK FlowIsn="22"/>
              </LogicLine>
            </LogicLines>
          </LogicUnit>
        </TaskLogic>
        <TaskForms>
          <FormEntry id="1">
            <PropertyList model="FORM_GUI0">
              <_Comment id="218"/>
              <FormName id="311" valUnicode="EX_CG01619VCFf_OS"/>
              <PersistentFormState id="493"/>
            </PropertyList>
          </FormEntry>
        </TaskForms>
        <Expressions>
          <Expression id="1">
            <ExpSyntax val="VarCurrN('v_OSInicial') = VarCurrN('v_OSFinal') AND VarCurrN('v_itemInicial') = VarCurrN('v_itemFinal')"/>
            <ExpAttribute val="B"/>
          </Expression>
          <Expression id="2">
            <ExpSyntax val="VarSet(VarIndex('v_filtroUnicoItem'), 'FALSE'LOG)"/>
            <ExpAttribute val="B"/>
          </Expression>
          <Expression id="3">
            <ExpSyntax val="VarSet(VarIndex('f_separarMat/Serv'), 'TRUE'LOG)"/>
            <ExpAttribute val="B"/>
          </Expression>
          <Expression id="4">
            <ExpSyntax val="VarSet(VarIndex('f_condPagServico'), {0,3})"/>
            <ExpAttribute val="B"/>
          </Expression>
          <Expression id="5">
            <ExpSyntax val="VarSet(VarIndex('f_tipoPagamentoServico'), {0,4})"/>
            <ExpAttribute val="B"/>
          </Expression>
          <Expression id="6">
            <ExpSyntax val="VarSet(VarIndex('f_condPagMaterial'), {0,7})"/>
            <ExpAttribute val="B"/>
          </Expression>
          <Expression id="7">
            <ExpSyntax val="VarSet(VarIndex('f_tipoPagamentoMaterial'), {0,8})"/>
            <ExpAttribute val="B"/>
          </Expression>
          <Expression id="8">
            <ExpSyntax val="VarCurrN('v_OSInicial')"/>
            <ExpAttribute val="*"/>
          </Expression>
          <Expression id="9">
            <ExpSyntax val="CndRange(VarCurrN('v_itemInicial') > 0, VarCurrN('v_itemInicial'))"/>
            <ExpAttribute val="*"/>
          </Expression>
        </Expressions>
        <Task MainProgram="N">
          <Header Description="BETA" ISN_2="2" LastIsn="2" id="61">
            <ExecutionRight comp="-1"/>
            <Resident val="N"/>
            <SQL val="N"/>
            <ReturnValue>
              <ReturnValueAttr/>
              <ParametersAttributes/>
            </ReturnValue>
            <SqlWhereExist val="N"/>
            <TaskType val="B"/>
            <External val="N"/>
            <FormType val="N"/>
            <DotNetObjectExists val="N"/>
            <LastModified _date="736671" _time="53657" date="08/12/2017" time="14:54:17"/>
          </Header>
          <Resource>
            <Columns/>
          </Resource>
          <Information>
            <Key>
              <Mode val="N"/>
            </Key>
            <DB comp="-1"/>
            <Sort>
              <CLS val="A"/>
            </Sort>
            <ForceRecordDelete DEL="N"/>
            <EndTaskCondition val="Y"/>
            <EvaluateEndCondition val="A"/>
            <InitialMode val="E"/>
            <Locate Direction="A"/>
            <Range Direction="A"/>
            <VarRange/>
            <TaskProperties>
              <SelectionTable val="N"/>
              <ConfirmUpdate CNFU="N"/>
              <ConfirmCancel val="N"/>
              <ErrorStrategy val="A"/>
              <LockingStrategy val="M"/>
              <CacheStrategy val="N"/>
              <ForceRecordSuffix val="N"/>
              <TransactionMode val="P"/>
              <TransactionBegin val="N"/>
              <PreloadView val="N"/>
              <AllowEmptyDataview val="Y"/>
              <KeepCreatedContext val="N"/>
            </TaskProperties>
            <SIDE_WIN>
              <AllowOptions val="N"/>
              <AllowQuery val="Y"/>
              <AllowModify val="N"/>
              <AllowCreate val="N"/>
              <AllowDelete val="N"/>
              <AllowLocate val="Y"/>
              <AllowRange val="Y"/>
              <AllowIndexChange val="Y"/>
              <AllowSorting val="Y"/>
              <AllowIOFiles val="Y"/>
              <RecordCycle val="Y"/>
              <AllowEvents val="Y"/>
              <AllowIndexOptimization val="Y"/>
              <AllowLocationInQuery val="Y"/>
              <AllowPrintingData val="N"/>
            </SIDE_WIN>
            <WIN>
              <OpenTaskWindow val="N"/>
              <CloseTaskWindow val="Y"/>
              <ForegroundWindow val="Y"/>
              <FlipFld val="N"/>
              <RefreshTaskWindow ReturnValue="N"/>
            </WIN>
            <BOX>
              <Direction val="V"/>
            </BOX>
          </Information>
          <TaskLogic>
            <LogicUnit id="2" propagate="78">
              <Level val="R"/>
              <Type val="M"/>
              <Scope val="S"/>
              <EngineDirective val="S"/>
              <ShowMessage val="Y"/>
              <Condition val="89"/>
              <Event>
                <EventType val="S"/>
                <PublicObject comp="-1"/>
              </Event>
              <LogicLines>
                <LogicLine>
                  <DATAVIEW_SRC FlowIsn="2" Type="M">
                    <Condition val="N"/>
                    <Modifier val="B"/>
                    <Direction val="C"/>
                  </DATAVIEW_SRC>
                </LogicLine>
                <LogicLine>
                  <Remark FlowIsn="3">
                    <Type val="1"/>
                    <Text val="O.S.: 509587/8 - 08/12/17 - JOM"/>
                  </Remark>
                </LogicLine>
                <LogicLine>
                  <Remark FlowIsn="4">
                    <Type val="0"/>
                    <Text val="Criado componente para executar ao modificar os filtros de OS e item"/>
                  </Remark>
                </LogicLine>
              </LogicLines>
            </LogicUnit>
          </TaskLogic>
          <TaskForms>
            <FormEntry id="1">
              <PropertyList model="FORM_GUI0">
                <_Comment id="218"/>
                <FormName id="311" valUnicode="BETA"/>
                <PersistentFormState id="493"/>
              </PropertyList>
            </FormEntry>
          </TaskForms>
        </Task>
      </Task>
    </Programs>
  </ProgramsRepository>

</Application>
